odoo10_addon_pos_report_session_summary-10.0.1.0.0.99.dev8-py3.8-nspkg.pth
odoo/addons/pos_report_session_summary/README.rst
odoo/addons/pos_report_session_summary/__init__.py
odoo/addons/pos_report_session_summary/__manifest__.py
odoo/addons/pos_report_session_summary/session_summary_report.xml
odoo/addons/pos_report_session_summary/i18n/ca.po
odoo/addons/pos_report_session_summary/i18n/es.po
odoo/addons/pos_report_session_summary/i18n/fr.po
odoo/addons/pos_report_session_summary/i18n/pos_report_session_summary.pot
odoo/addons/pos_report_session_summary/readme/DESCRIPTION.rst
odoo/addons/pos_report_session_summary/readme/USAGE.rst
odoo/addons/pos_report_session_summary/static/description/icon.png
odoo/addons/pos_report_session_summary/static/description/index.html
odoo/addons/pos_report_session_summary/views/report_session_summary.xml
odoo10_addon_pos_report_session_summary-10.0.1.0.0.99.dev8.dist-info/METADATA
odoo10_addon_pos_report_session_summary-10.0.1.0.0.99.dev8.dist-info/WHEEL
odoo10_addon_pos_report_session_summary-10.0.1.0.0.99.dev8.dist-info/namespace_packages.txt
odoo10_addon_pos_report_session_summary-10.0.1.0.0.99.dev8.dist-info/top_level.txt
odoo10_addon_pos_report_session_summary-10.0.1.0.0.99.dev8.dist-info/RECORD
