Metadata-Version: 2.1
Name: odoo10-addon-pos-report-session-summary
Version: 10.0.1.0.0.99.dev8
Summary: Adds a Session Summary PDF report on the POS session
Home-page: https://github.com/OCA/pos
Author: Akretion, Odoo SA, Odoo Community Association (OCA)
Author-email: support@odoo-community.org
License: LGPL-3
Platform: UNKNOWN
Classifier: Programming Language :: Python
Classifier: Framework :: Odoo
Classifier: Framework :: Odoo :: 10.0
Classifier: License :: OSI Approved :: GNU Lesser General Public License v3 (LGPLv3)
Requires-Python: ~=2.7
Requires-Dist: odoo <10.1dev,>=10.0
